{
    "generated_time": "2023-11-09T23:40:33.723938",
    "stack_number": 61,
    "stacks": [
        {
            "id": "00000039",
            "department": "미래인재센터.채용공고",
            "timestamp": "2023-11-09T23:32:13.628647",
            "title": "오늘의 채용공고가 39건 있습니다",
            "keywords": [
                "미래인재센터",
                "2023-11-09",
                "취업"
            ],
            "url": "https://goodjob.khu.ac.kr/bbs/board.php?bo_table=s3_3&page=3"
        },
        {
            "id": "00000018",
            "department": "학생회관(국제).학생식당",
            "timestamp": "2023-11-09T00:00:54.183279",
            "title": "주간식단표 231106-1110",
            "keywords": [
                "학생회관(국제)",
                "2023-11-09",
                "학식"
            ],
            "url": "https://www.khu.ac.kr/kor/forum/list.do?type=RESTAURANT&category=INTL&page=1"
        },
        {
            "id": "0S000083",
            "department": "생활협동조합(서울).주간식당메뉴",
            "timestamp": "2023-11-09T00:11:52.291490",
            "title": "11월 2주차 청운관식당(학생/교직원) 주간메뉴표",
            "keywords": [
                "생활협동조합(서울)",
                "2023-11-09",
                "학식"
            ],
            "url": "https://coop.khu.ac.kr/9%ec%9b%94-3%ec%a3%bc%ec%b0%a8-%ec%a3%bc%ea%b0%84%eb%a9%94%eb%89%b4%ed%91%9c-2-copy-copy/"
        },
        {
            "id": "00000041",
            "department": "생체의공학과",
            "timestamp": "2023-11-09T08:32:31.444851",
            "title": "[홍보] 창업 시제품 제작 역량 강화 프로그램 참여자 모집 (접수 기간: - 11/13 15시)",
            "keywords": [
                "생체의공학과",
                "2023-11-09",
                "모집",
                "창업"
            ],
            "url": "https://bme.khu.ac.kr/bme/user/bbs/BMSR00040/list.do?menuNo=1800030&pageIndex=1&searchCondition=&searchKeyword="
        },
        {
            "id": "00000045",
            "department": "전자공학과.홍보및대외활동",
            "timestamp": "2023-11-09T08:32:47.208078",
            "title": "[홍보] 창업 시제품 제작 역량 강화 프로그램 참여자 모집 (접수 기간: - 11/13 15시)",
            "keywords": [
                "전자공학과",
                "2023-11-09",
                "모집",
                "창업"
            ],
            "url": "https://ee.khu.ac.kr/ee/user/bbs/BMSR00040/list.do?menuNo=1900039&pageIndex=1&searchCondition=&searchKeyword="
        },
        {
            "id": "0S000080",
            "department": "경영대학원",
            "timestamp": "2023-11-09T09:10:36.074753",
            "title": "2023-2 논문예비계획서 제출자 논문지도교수 배정 안내",
            "keywords": [
                "경영대학원",
                "2023-11-09",
                "논문"
            ],
            "url": "https://khmba.khu.ac.kr/khmba_kor/user/bbs/BMSR00040/list.do?menuNo=10800152&pageIndex=1&searchCategory=&searchCondition=&searchKeyword="
        },
        {
            "id": "0S000080",
            "department": "경영대학원",
            "timestamp": "2023-11-09T09:10:36.075410",
            "title": "2023-2 논문예비계획서 제출자 논문지도교수 배정 안내",
            "keywords": [
                "경영대학원",
                "2023-11-09",
                "논문"
            ],
            "url": "https://khmba.khu.ac.kr/khmba_kor/user/bbs/BMSR00040/list.do?menuNo=10800152&pageIndex=1&searchCategory=&searchCondition=&searchKeyword="
        },
        {
            "id": "00000019",
            "department": "우정원",
            "timestamp": "2023-11-09T09:30:46.611479",
            "title": "[11/16] 우정원 승강기 정기점검 시행 안내 NEW",
            "keywords": [
                "우정원",
                "2023-11-09",
                "기숙사"
            ],
            "url": "https://wjwdorm.khu.ac.kr/60/6010.kmc"
        },
        {
            "id": "00000033",
            "department": "외국어대학",
            "timestamp": "2023-11-09T09:31:41.947585",
            "title": "제1회 동국·판타지오 드라마 극본 공모전 개최 안내",
            "keywords": [
                "외국어대학",
                "2023-11-09",
                "공모전"
            ],
            "url": "http://foreign.khu.ac.kr/contents/bbs/bbs_list.html?bbs_cls_cd=002004014"
        },
        {
            "id": "00000077",
            "department": "한국어학과.취업정보",
            "timestamp": "2023-11-09T09:34:07.667455",
            "title": "[카카오] 2024 채용 연계형 겨울 인턴십 모집(11/8~11/20)",
            "keywords": [
                "한국어학과",
                "2023-11-09",
                "모집",
                "취업"
            ],
            "url": "http://korean.khu.ac.kr/contents/bbs/bbs_list.html?bbs_cls_cd=002004004"
        },
        {
            "id": "00000077",
            "department": "한국어학과.취업정보",
            "timestamp": "2023-11-09T09:34:07.693598",
            "title": "[롯데그룹] LOTTE Job Cafe에 초대합니다!",
            "keywords": [
                "한국어학과",
                "2023-11-09",
                "취업"
            ],
            "url": "http://korean.khu.ac.kr/contents/bbs/bbs_list.html?bbs_cls_cd=002004004"
        },
        {
            "id": "00000077",
            "department": "한국어학과.취업정보",
            "timestamp": "2023-11-09T09:34:07.717193",
            "title": "[KOMEA] 2023 조선해양산업 AI역량강화교육 신청 안내 (교육비 전액 무료)",
            "keywords": [
                "한국어학과",
                "2023-11-09",
                "취업"
            ],
            "url": "http://korean.khu.ac.kr/contents/bbs/bbs_list.html?bbs_cls_cd=002004004"
        },
        {
            "id": "00000081",
            "department": "한국어학과.자유게시판",
            "timestamp": "2023-11-09T09:34:22.442284",
            "title": "[교수학습개발원] 학습법 특강 8-9-10차 신청 안내: 챗GPT 활용법 & 디지...",
            "keywords": [
                "한국어학과",
                "2023-11-09",
                "강연"
            ],
            "url": "http://korean.khu.ac.kr/contents/bbs/bbs_list.html?bbs_cls_cd=002004002"
        },
        {
            "id": "00000073",
            "department": "한국어학과",
            "timestamp": "2023-11-09T10:03:55.448040",
            "title": "[국립국어원]2023년 제3차 한국어교원 자격 부여(개인 자격 심사) 안내",
            "keywords": [
                "한국어학과",
                "2023-11-09",
                "기타"
            ],
            "url": "http://korean.khu.ac.kr/contents/bbs/bbs_list.html?bbs_cls_cd=002004001"
        },
        {
            "id": "00000077",
            "department": "한국어학과.취업정보",
            "timestamp": "2023-11-09T10:04:09.805686",
            "title": "노루페인트/ 노루알앤씨 / 노루케미칼 신규직원 채용",
            "keywords": [
                "한국어학과",
                "2023-11-09",
                "취업"
            ],
            "url": "http://korean.khu.ac.kr/contents/bbs/bbs_list.html?bbs_cls_cd=002004004"
        },
        {
            "id": "0S000062",
            "department": "간호과학대학",
            "timestamp": "2023-11-09T10:10:36.449143",
            "title": "[일반] [3학년 대상] 삼성강북병원 채용연계형 간호인턴 NURSE GENIUS 안내",
            "keywords": [
                "간호과학대학",
                "2023-11-09",
                "취업"
            ],
            "url": "https://khcns21.khu.ac.kr/index/community/notice_1.php?&page=1"
        },
        {
            "id": "0S000062",
            "department": "간호과학대학",
            "timestamp": "2023-11-09T10:10:36.987450",
            "title": "[일반] [3학년 대상] 삼성강북병원 채용연계형 간호인턴 NURSE GENIUS 안내",
            "keywords": [
                "간호과학대학",
                "2023-11-09",
                "취업"
            ],
            "url": "https://khcns21.khu.ac.kr/index/community/notice_1.php?&page=1"
        },
        {
            "id": "00000058",
            "department": "정보전자신소재공학과",
            "timestamp": "2023-11-09T10:33:24.414655",
            "title": "[국제C] 2023학년도 2학기 장학팀 장학사정관제장학 신청 안내",
            "keywords": [
                "정보전자신소재공학과",
                "2023-11-09",
                "장학"
            ],
            "url": "https://eng.khu.ac.kr/amie/C1350327?page=1&category=&"
        },
        {
            "id": "00000059",
            "department": "정보전자신소재공학과.취업게시판",
            "timestamp": "2023-11-09T10:33:25.962019",
            "title": "코멘토(comento) 온라인 취업교육 통합 프로그램 서비스",
            "keywords": [
                "정보전자신소재공학과",
                "2023-11-09",
                "온라인",
                "취업"
            ],
            "url": "https://eng.khu.ac.kr/amie/C2130308?page=1&category=&"
        },
        {
            "id": "00000059",
            "department": "정보전자신소재공학과.취업게시판",
            "timestamp": "2023-11-09T10:33:25.962299",
            "title": "2023학년도 2학기 NCS기반 공기업 대비반 참여자 모집",
            "keywords": [
                "정보전자신소재공학과",
                "2023-11-09",
                "모집",
                "취업"
            ],
            "url": "https://eng.khu.ac.kr/amie/C2130308?page=1&category=&"
        },
        {
            "id": "0S000005",
            "department": "영어영문학과",
            "timestamp": "2023-11-09T10:36:12.941967",
            "title": "학사 2023학년도 영어영문학과 동계 해외 전공연수 안내",
            "keywords": [
                "영어영문학과",
                "2023-11-09",
                "연수"
            ],
            "url": "http://khenglish.khu.ac.kr/contents/bbs/bbs_list.html?bbs_cls_cd=002004001"
        },
        {
            "id": "0S000007",
            "department": "영어영문학과.취업정보",
            "timestamp": "2023-11-09T10:36:22.101308",
            "title": "[그린서비스] 11월 29-30일 서울 코엑스 상담회 통역사 모집 ...",
            "keywords": [
                "영어영문학과",
                "2023-11-09",
                "모집",
                "취업"
            ],
            "url": "http://khenglish.khu.ac.kr/contents/bbs/bbs_list.html?bbs_cls_cd=002004002"
        },
        {
            "id": "0S000054",
            "department": "무역학과",
            "timestamp": "2023-11-09T10:39:35.089951",
            "title": "2023학년도 동계 계절학기 수업 운영 안내",
            "keywords": [
                "무역학과",
                "2023-11-09",
                "계절학기"
            ],
            "url": "http://trade.khu.ac.kr/trade/index.php?mid=notice&page=1"
        },
        {
            "id": "0S000058",
            "department": "의과대학",
            "timestamp": "2023-11-09T10:39:47.072689",
            "title": "[일반] 제 7기 2023년 동계 서울대학교 대학원 융합전공 혁신의과학 학부연구생 인턴 모집",
            "keywords": [
                "의과대학",
                "2023-11-09",
                "모집"
            ],
            "url": "https://khusm.khu.ac.kr/bbs/board.php?bo_table=s6_1&page=1"
        },
        {
            "id": "0S000026",
            "department": "이과대학.연구/세미나",
            "timestamp": "2023-11-09T11:07:16.792350",
            "title": "2023 서울 빅데이터 포럼 개최 안내",
            "keywords": [
                "이과대학",
                "2023-11-09",
                "기타"
            ],
            "url": "https://science.khu.ac.kr/science_kor/user/bbs/BMSR00040/list.do?menuNo=1200040&pageIndex=1&searchCondition=&searchKeyword="
        },
        {
            "id": "0S000068",
            "department": "경영대학",
            "timestamp": "2023-11-09T11:09:38.374252",
            "title": "★중요★ 2023학년도 2학기 졸업시험(2차) 및 면제신청(2차) 안내",
            "keywords": [
                "경영대학",
                "2023-11-09",
                "졸업"
            ],
            "url": "https://kbiz.khu.ac.kr/board5/bbs/board.php?bo_table=05_04_01&page=1"
        },
        {
            "id": "00000068",
            "department": "원자력공학과",
            "timestamp": "2023-11-09T11:33:42.669491",
            "title": "[원자력학회] 2023 원자력 영 파워 (Young Power) 글로벌 프로그램 홍보 및 참여 안내",
            "keywords": [
                "원자력공학과",
                "2023-11-09",
                "기타"
            ],
            "url": "https://eng.khu.ac.kr/ne/C0880336?page=1&category=&"
        },
        {
            "id": "00000090",
            "department": "일반대학원",
            "timestamp": "2023-11-09T13:35:12.596969",
            "title": "(공통) [과학기술인공제회] 2023년 신입직원(정규직) 채용 공고",
            "keywords": [
                "일반대학원",
                "2023-11-09",
                "취업"
            ],
            "url": "https://gskh.khu.ac.kr/index/s8_comm/comm_1.php?&page=1"
        },
        {
            "id": "0S000020",
            "department": "약학대학",
            "timestamp": "2023-11-09T13:37:09.620988",
            "title": "[한국파스퇴르연구소] 2024년 동계 대학생 바이오 인턴십 안내",
            "keywords": [
                "약학대학",
                "2023-11-09",
                "기타"
            ],
            "url": "https://pharm.khu.ac.kr/pharm_kor/user/bbs/BMSR00040/list.do?menuNo=3900106&pageIndex=3&searchCondition=&searchKeyword="
        },
        {
            "id": "0S000079",
            "department": "공공대학원",
            "timestamp": "2023-11-09T13:40:38.960356",
            "title": "2023년 천문대 공개관측회 개최 및 프로그램 안내",
            "keywords": [
                "공공대학원",
                "2023-11-09",
                "기타"
            ],
            "url": "https://pnc.khu.ac.kr/pnc/user/bbs/BMSR00049/list.do?menuNo=800202&pageIndex=1&searchGubunCd=&searchCondition=&searchKeyword="
        },
        {
            "id": "00000038",
            "department": "미래혁신원.학생지원센터(장학)",
            "timestamp": "2023-11-09T14:02:17.870931",
            "title": "[공통][교외][11.13~12.08] 2024 에몬스 장학생 선발 안내",
            "keywords": [
                "미래혁신원",
                "2023-11-09",
                "장학"
            ],
            "url": "https://janghak.khu.ac.kr/janghak/user/bbs/BMSR00040/list.do?menuNo=12300032&pageIndex=1&searchCategory=&searchCondition=&searchKeyword="
        },
        {
            "id": "00000070",
            "department": "프랑스어학과",
            "timestamp": "2023-11-09T14:03:55.284174",
            "title": "2023년 전공탐색세미나 졸업생 특강 (유통업계의 이해: 백화점 업계 흐름과 영업관...",
            "keywords": [
                "프랑스어학과",
                "2023-11-09",
                "강연",
                "세미나",
                "졸업"
            ],
            "url": "http://france.khu.ac.kr/contents/bbs/bbs_list.html?bbs_cls_cd=002004001"
        },
        {
            "id": "00000074",
            "department": "프랑스어학과.취업정보",
            "timestamp": "2023-11-09T14:04:22.532202",
            "title": "[세아상역] 아르바이트 모집 협조 요청",
            "keywords": [
                "프랑스어학과",
                "2023-11-09",
                "모집",
                "취업"
            ],
            "url": "http://france.khu.ac.kr/contents/bbs/bbs_list.html?bbs_cls_cd=002004004"
        },
        {
            "id": "00000094",
            "department": "대학생활(일반)",
            "timestamp": "2023-11-09T14:05:35.742914",
            "title": "(캠퍼스:공통) 2023학년도 KHU Global Ambassadors...",
            "keywords": [
                "대학생활(일반)",
                "2023-11-09",
                "기타"
            ],
            "url": "https://www.khu.ac.kr/kor/notice/list.do?page=1&category=GENERAL"
        },
        {
            "id": "00000094",
            "department": "대학생활(일반)",
            "timestamp": "2023-11-09T14:05:35.798059",
            "title": "(캠퍼스:공통) [한국장학재단]2023 동계 재능봉사 캠프 멘토팀 모집",
            "keywords": [
                "대학생활(일반)",
                "2023-11-09",
                "모집",
                "장학"
            ],
            "url": "https://www.khu.ac.kr/kor/notice/list.do?page=1&category=GENERAL"
        },
        {
            "id": "00000094",
            "department": "대학생활(일반)",
            "timestamp": "2023-11-09T14:05:35.848176",
            "title": "(캠퍼스:공통) 등재지 『오토피아』 제38권 3호 원고 모집",
            "keywords": [
                "대학생활(일반)",
                "2023-11-09",
                "모집"
            ],
            "url": "https://www.khu.ac.kr/kor/notice/list.do?page=1&category=GENERAL"
        },
        {
            "id": "00000095",
            "department": "대학생활(장학)",
            "timestamp": "2023-11-09T14:05:40.142497",
            "title": "(캠퍼스:공통) [공통][교외][11.13~12.08] 2024 에몬스...",
            "keywords": [
                "대학생활(장학)",
                "2023-11-09",
                "장학"
            ],
            "url": "https://www.khu.ac.kr/kor/notice/list.do?category=SCHOLARSHIP&page=1"
        },
        {
            "id": "00000096",
            "department": "대학생활(교내학점교류)",
            "timestamp": "2023-11-09T14:05:44.876248",
            "title": "(캠퍼스:국제) [한세대학교] 2023학년도 동계계절학기 경인지역 학점...",
            "keywords": [
                "대학생활(교내학점교류)",
                "2023-11-09",
                "계절학기"
            ],
            "url": "https://www.khu.ac.kr/kor/notice/list.do?category=CREDIT&page=1"
        },
        {
            "id": "00000070",
            "department": "프랑스어학과",
            "timestamp": "2023-11-09T14:34:03.244434",
            "title": "RENCONTRES AFFAIRES 2023 - 프랑스어 관련 학과 학생과 프랑스어권 기업의 만남",
            "keywords": [
                "프랑스어학과",
                "2023-11-09",
                "기타"
            ],
            "url": "http://france.khu.ac.kr/contents/bbs/bbs_list.html?bbs_cls_cd=002004001"
        },
        {
            "id": "00000070",
            "department": "프랑스어학과",
            "timestamp": "2023-11-09T14:34:03.262467",
            "title": "RENCONTRES AFFAIRES 2023 - 프랑스어 관련 학과 학생과 프랑스어권 기업의 만남",
            "keywords": [
                "프랑스어학과",
                "2023-11-09",
                "기타"
            ],
            "url": "http://france.khu.ac.kr/contents/bbs/bbs_list.html?bbs_cls_cd=002004001"
        },
        {
            "id": "00000078",
            "department": "프랑스어학과.자유게시판",
            "timestamp": "2023-11-09T14:34:32.965033",
            "title": "[2023/11/8] 기후전문가들 “12만 5000년 만에 올해가 가장 뜨거운 해”",
            "keywords": [
                "프랑스어학과",
                "2023-11-09",
                "기타"
            ],
            "url": "http://france.khu.ac.kr/contents/bbs/bbs_list.html?bbs_cls_cd=002004002"
        },
        {
            "id": "0S000068",
            "department": "경영대학",
            "timestamp": "2023-11-09T14:39:59.700455",
            "title": "2023학년도 윤병강 장학회 선발자 안내",
            "keywords": [
                "경영대학",
                "2023-11-09",
                "장학"
            ],
            "url": "https://kbiz.khu.ac.kr/board5/bbs/board.php?bo_table=05_04_01&page=1"
        },
        {
            "id": "00000021",
            "department": "중앙도서관(국제)",
            "timestamp": "2023-11-09T15:00:56.428749",
            "title": "KISA 국가기술자격증 응원선물 이벤트 당첨자 안내",
            "keywords": [
                "중앙도서관(국제)",
                "2023-11-09",
                "이벤트",
                "자격증"
            ],
            "url": "https://library.khu.ac.kr/global/blog/KISA-9/110/31"
        },
        {
            "id": "0S000018",
            "department": "무용학부",
            "timestamp": "2023-11-09T15:07:21.090243",
            "title": "2024학년도 1학기 캡스톤디자인 과목 수강신청 및 수강 안내",
            "keywords": [
                "무용학부",
                "2023-11-09",
                "수강신청"
            ],
            "url": "https://dance.khu.ac.kr/dance/user/bbs/BMSR00040/list.do?menuNo=300049&pageIndex=2&searchCondition=&searchKeyword="
        },
        {
            "id": "0S000067",
            "department": "식품영양학과",
            "timestamp": "2023-11-09T15:10:28.898729",
            "title": "2024학년도 1학기 캡스톤디자인 과목 수강신청 및 수강 안내",
            "keywords": [
                "식품영양학과",
                "2023-11-09",
                "수강신청"
            ],
            "url": "https://che.khu.ac.kr/che/user/bbs/BMSR00040/list.do?menuNo=12700018&pageIndex=1&searchCategory=&searchCondition=&searchKeyword="
        },
        {
            "id": "00000090",
            "department": "일반대학원",
            "timestamp": "2023-11-09T15:34:55.050004",
            "title": "(공통) [경희대학교 인류사회재건연구원] 등재학술지 OUGHTOPIA(오토피아) 제38권 3호 …",
            "keywords": [
                "일반대학원",
                "2023-11-09",
                "기타"
            ],
            "url": "https://gskh.khu.ac.kr/index/s8_comm/comm_1.php?&page=1"
        },
        {
            "id": "0S000014",
            "department": "호텔관광대학.학사공지사항",
            "timestamp": "2023-11-09T15:36:26.955038",
            "title": "2024학년도 1학기 캡스톤디자인 과목 수강 안내",
            "keywords": [
                "호텔관광대학",
                "2023-11-09",
                "기타"
            ],
            "url": "https://hot.khu.ac.kr/hot20_kor/user/bbs/BMSR00040/list.do?menuNo=10900107&pageIndex=1&searchCondition=&searchKeyword="
        },
        {
            "id": "0S000026",
            "department": "이과대학.연구/세미나",
            "timestamp": "2023-11-09T15:37:19.034038",
            "title": "서울시 양자기술산업 육성을 위한「서울퀀텀플랫폼 포럼」안내",
            "keywords": [
                "이과대학",
                "2023-11-09",
                "기타"
            ],
            "url": "https://science.khu.ac.kr/science_kor/user/bbs/BMSR00040/list.do?menuNo=1200040&pageIndex=1&searchCondition=&searchKeyword="
        },
        {
            "id": "0S000028",
            "department": "수학과",
            "timestamp": "2023-11-09T16:08:23.188424",
            "title": "2024학년도 1학기 캡스톤디자인 교과목 운영 안내",
            "keywords": [
                "수학과",
                "2023-11-09",
                "기타"
            ],
            "url": "https://maths.khu.ac.kr/maths/user/bbs/BMSR00040/list.do?menuNo=600017&pageIndex=2&searchCondition=&searchKeyword="
        },
        {
            "id": "0S000068",
            "department": "경영대학",
            "timestamp": "2023-11-09T16:10:38.171877",
            "title": "2024학년도 1학기 캡스톤디자인 과목 수강신청 및 수강 안내",
            "keywords": [
                "경영대학",
                "2023-11-09",
                "수강신청"
            ],
            "url": "https://kbiz.khu.ac.kr/board5/bbs/board.php?bo_table=05_04_01&page=1"
        },
        {
            "id": "00000070",
            "department": "프랑스어학과",
            "timestamp": "2023-11-09T16:34:07.711198",
            "title": "RENCONTRES AFFAIRES 2023 - 프랑스어 관련 학과 학생과 프랑스어권 기업의 만남 (...",
            "keywords": [
                "프랑스어학과",
                "2023-11-09",
                "기타"
            ],
            "url": "http://france.khu.ac.kr/contents/bbs/bbs_list.html?bbs_cls_cd=002004001"
        },
        {
            "id": "00000070",
            "department": "프랑스어학과",
            "timestamp": "2023-11-09T16:34:07.727799",
            "title": "RENCONTRES AFFAIRES 2023 - 프랑스어 관련 학과 학생과 프랑스어권 기업의 만남 (...",
            "keywords": [
                "프랑스어학과",
                "2023-11-09",
                "기타"
            ],
            "url": "http://france.khu.ac.kr/contents/bbs/bbs_list.html?bbs_cls_cd=002004001"
        },
        {
            "id": "00000038",
            "department": "미래혁신원.학생지원센터(장학)",
            "timestamp": "2023-11-09T17:02:08.012662",
            "title": "[공통][교외] 2024 아인슈타인 클래스 15기 대학생 멘토 선발 안내[10.23~11.12]",
            "keywords": [
                "미래혁신원",
                "2023-11-09",
                "장학"
            ],
            "url": "https://janghak.khu.ac.kr/janghak/user/bbs/BMSR00040/list.do?menuNo=12300032&pageIndex=1&searchCategory=&searchCondition=&searchKeyword="
        },
        {
            "id": "00000095",
            "department": "대학생활(장학)",
            "timestamp": "2023-11-09T17:05:28.214395",
            "title": "(캠퍼스:공통) [공통][교외] 2024 아인슈타인 클래스 15기 대학...",
            "keywords": [
                "대학생활(장학)",
                "2023-11-09",
                "장학"
            ],
            "url": "https://www.khu.ac.kr/kor/notice/list.do?category=SCHOLARSHIP&page=1"
        },
        {
            "id": "0S000021",
            "department": "미술대학",
            "timestamp": "2023-11-09T17:07:09.822068",
            "title": "2024학년도 1학기 캡스톤 디자인 교과목 운영 안내문",
            "keywords": [
                "미술대학",
                "2023-11-09",
                "기타"
            ],
            "url": "https://khuart.khu.ac.kr/khuart/user/bbs/BMSR00040/list.do?menuNo=1400031&pageIndex=1&searchCondition=&searchKeyword="
        },
        {
            "id": "00000075",
            "department": "러시아어학과.취업정보",
            "timestamp": "2023-11-09T17:34:02.694388",
            "title": "[카카오] 2024 채용 연계형 겨울 인턴십",
            "keywords": [
                "러시아어학과",
                "2023-11-09",
                "취업"
            ],
            "url": "http://russia.khu.ac.kr/contents/bbs/bbs_list.html?bbs_cls_cd=002004004"
        },
        {
            "id": "00000075",
            "department": "러시아어학과.취업정보",
            "timestamp": "2023-11-09T17:34:02.717676",
            "title": "[현대자동차그룹] 소프티어 부트캠프 3기 모집(~11/13(월) 14시까지)",
            "keywords": [
                "러시아어학과",
                "2023-11-09",
                "모집",
                "취업"
            ],
            "url": "http://russia.khu.ac.kr/contents/bbs/bbs_list.html?bbs_cls_cd=002004004"
        },
        {
            "id": "00000075",
            "department": "러시아어학과.취업정보",
            "timestamp": "2023-11-09T17:34:02.738515",
            "title": "[롯데그룹] LOTTE Job Cafe",
            "keywords": [
                "러시아어학과",
                "2023-11-09",
                "취업"
            ],
            "url": "http://russia.khu.ac.kr/contents/bbs/bbs_list.html?bbs_cls_cd=002004004"
        },
        {
            "id": "00000075",
            "department": "러시아어학과.취업정보",
            "timestamp": "2023-11-09T17:34:02.757616",
            "title": "[KOMEA] 2023 조선해양산업 AI역량강화교육 신청 안내 (교육비 전액 무료)",
            "keywords": [
                "러시아어학과",
                "2023-11-09",
                "취업"
            ],
            "url": "http://russia.khu.ac.kr/contents/bbs/bbs_list.html?bbs_cls_cd=002004004"
        },
        {
            "id": "00000075",
            "department": "러시아어학과.취업정보",
            "timestamp": "2023-11-09T17:34:02.777092",
            "title": "[삼양그룹] 2023년 10월 삼양그룹 수시채용(~11/13(월) 9시까지)",
            "keywords": [
                "러시아어학과",
                "2023-11-09",
                "취업"
            ],
            "url": "http://russia.khu.ac.kr/contents/bbs/bbs_list.html?bbs_cls_cd=002004004"
        },
        {
            "id": "00000079",
            "department": "러시아어학과.자유게시판",
            "timestamp": "2023-11-09T17:34:18.296498",
            "title": "[한국외대 TESOL 대학원] 2024 전기 일반전형 입시 홍보",
            "keywords": [
                "러시아어학과",
                "2023-11-09",
                "기타"
            ],
            "url": "http://russia.khu.ac.kr/contents/bbs/bbs_list.html?bbs_cls_cd=002004002"
        }
    ]
}