{
    "generated_time": "2023-10-21T23:41:00.495089",
    "stack_number": 4,
    "stacks": [
        {
            "id": "0S000056",
            "department": "국제통상-금융투자학부",
            "timestamp": "2023-10-21T09:09:22.470126",
            "title": "학습법 특강 안내(6차/7차)",
            "keywords": [
                "국제통상-금융투자학부",
                "2023-10-21",
                "강연"
            ],
            "url": "http://cominv.khu.ac.kr/home/index.php?mid=notice&page=1"
        },
        {
            "id": "00000026",
            "department": "국제대학.채용.인턴.활동",
            "timestamp": "2023-10-21T10:31:15.704994",
            "title": "[현대자동차] NextGen 인턴십 채용 홍보",
            "keywords": [
                "국제대학",
                "2023-10-21",
                "취업"
            ],
            "url": "https://kic.khu.ac.kr/kic_kor/user/bbs/BMSR00040/list.do?menuNo=5000031&pageIndex=1&searchCondition=&searchKeyword="
        },
        {
            "id": "00000026",
            "department": "국제대학.채용.인턴.활동",
            "timestamp": "2023-10-21T15:01:22.168946",
            "title": "교내프로그램 홍보 프로젝트 KHU Careers Editor 양성과정 7기 참여자 모집 및 홍보",
            "keywords": [
                "국제대학",
                "2023-10-21",
                "모집",
                "취업"
            ],
            "url": "https://kic.khu.ac.kr/kic_kor/user/bbs/BMSR00040/list.do?menuNo=5000031&pageIndex=1&searchCondition=&searchKeyword="
        },
        {
            "id": "00000089",
            "department": "동서의학대학원",
            "timestamp": "2023-10-21T15:34:52.727744",
            "title": "2024학년도 전기 신입생모집 입시설명회(영상 및 PDF자료)",
            "keywords": [
                "동서의학대학원",
                "2023-10-21",
                "강연",
                "모집"
            ],
            "url": "http://gsm.khu.ac.kr/bbs/board.php?bo_table=notice&page=1"
        }
    ]
}