{
    "generated_time": "2023-06-06T23:41:22.665018",
    "stack_number": 2,
    "stacks": [
        {
            "id": "00000018",
            "department": "학생회관(국제).학생식당",
            "timestamp": "2023-06-06T00:00:34.979826",
            "title": "(주간식단표0605~0609)",
            "keywords": [
                "학생회관(국제)",
                "2023-06-06",
                "학식"
            ],
            "url": "https://www.khu.ac.kr/kor/forum/list.do?type=RESTAURANT&category=INTL&page=1"
        },
        {
            "id": "00000056",
            "department": "화학공학과",
            "timestamp": "2023-06-06T13:33:18.580265",
            "title": "화공과 대학원맛보기프로그램2 선정결과",
            "keywords": [
                "화학공학과",
                "2023-06-06",
                "프로그램"
            ],
            "url": "https://eng.khu.ac.kr/chemeng/C1970353?page=1&category=&"
        }
    ]
}